xiaoai/server.py
mcp_xiaoai_hass-0.1.0.dist-info/METADATA
mcp_xiaoai_hass-0.1.0.dist-info/WHEEL
mcp_xiaoai_hass-0.1.0.dist-info/entry_points.txt
mcp_xiaoai_hass-0.1.0.dist-info/top_level.txt
mcp_xiaoai_hass-0.1.0.dist-info/RECORD
