Metadata-Version: 2.4
Name: mcp-xiaoai-hass
Version: 0.1.0
Summary: MCP server for xiaoai voice control
Author-email: Gemini Wen <coffeesherk@gmail.com>
Requires-Python: >=3.11
Requires-Dist: mcp
Requires-Dist: requests
